<?xml version="1.0"?>
<settings xmlns="urn:settings" xmlns:xs="http://www.w3.org/2001/XMLSchema-instance" xs:schemaLocation="urn:settings Settings.xsd">
	<list>
		<!--selectRowProperty="IsDefault"-->

		<global>
			<create/>
		</global>

		<actions>
			<visibility/>			
			<edit/>
			<delete/>
		</actions>

		<cols>			
		<string name="Article.Name" title="Статья"/>
	
			
		</cols>

	</list>

	<form>
		<tab name="General">

			<select name="ArticleId" title="Пост" reference="Article" optionTitle="Title" optionValue="Id" multiple="false" localizable="true">
			</select>

			
			<string name="Name" title="Имя"/>
			<string name="Email" title="Email"/>

			<select name="CrewMemberId" title="Автор" reference="CrewMember" optionTitle="FirstName" optionValue="Id" multiple="false" localizable="true">
				<option>Нет</option>
			</select>

			<select name="ParentId" title="Комент" reference="Parent" optionTitle="Id" optionValue="Id" multiple="false" localizable="true">
				<option>Нет</option>
			</select>

			<wysiwyg name="Content" title="Контент" />
			
		</tab>
   	
	</form>
</settings>